switchcraft/__init__.py
switchcraft/clients/__init__.py
switchcraft/clients/alb.py
switchcraft/clients/config.py
switchcraft/clients/dynamodb.py
switchcraft/clients/ec2.py
switchcraft/clients/organizations.py
switchcraft/clients/rds.py
switchcraft/clients/s3.py
switchcraft/clients/sns.py
switchcraft/clients/sts.py
switchcraft/conversion/__init__.py
switchcraft/conversion/arnparse/__init__.py
switchcraft/conversion/arnparse/arnparse.py
switchcraft/conversion/conversion.py
switchcraft/data_classes/__init__.py
switchcraft/data_classes/base.py
switchcraft/data_classes/config_event.py
switchcraft/data_classes/rds_db_instance.py
switchcraft/exceptions.py
switchcraft/package_logger.py
switchcraft-0.15.0.dist-info/LICENSE
switchcraft-0.15.0.dist-info/WHEEL
switchcraft-0.15.0.dist-info/METADATA
switchcraft-0.15.0.dist-info/RECORD
