Metadata-Version: 2.1
Name: switchcraft
Version: 0.15.0
Summary: Client wrappers and helpful utilities to solve common coding challenges in AWS
License: MIT-0
Keywords: switchcraft,aws,lambda
Author: WWPS ProServe
Requires-Python: >=3.7,<4.0
Classifier: Development Status :: 5 - Production/Stable
Classifier: Intended Audience :: Developers
Classifier: License :: OSI Approved :: MIT License
Classifier: License :: Other/Proprietary License
Classifier: Natural Language :: English
Classifier: Programming Language :: Python :: 3
Classifier: Programming Language :: Python :: 3.7
Classifier: Programming Language :: Python :: 3.8
Classifier: Programming Language :: Python :: 3.9
Requires-Dist: boto3 (>=1.16.3,<2.0.0)
Requires-Dist: pydantic (>=1.6.1,<2.0.0)
